cordlog/__init__.py
cordlog/discord.py
cordlog/formatter.py
cordlog/logger.py
cordlog/storage.py
cordlog/utils.py
cordlog-1.0.0.dist-info/METADATA
cordlog-1.0.0.dist-info/WHEEL
cordlog-1.0.0.dist-info/RECORD
