Metadata-Version: 2.3
Name: cordlog
Version: 1.0.0
Summary: Colored logging formatter for Python
Author: LordCode
Requires-Python: >=3.11,<4.0
Classifier: Programming Language :: Python :: 3
Classifier: Programming Language :: Python :: 3.11
Classifier: Programming Language :: Python :: 3.12
Classifier: Programming Language :: Python :: 3.13
Requires-Dist: aiohttp (>=3.11.18,<4.0.0)
Requires-Dist: requests (>=2.32.3,<3.0.0)
